NetAnalyzer/__init__.py
NetAnalyzer/adv_mat_calc.py
NetAnalyzer/cli_manager.py
NetAnalyzer/graph2sim.py
NetAnalyzer/integration.py
NetAnalyzer/main_modules.py
NetAnalyzer/net_parser.py
NetAnalyzer/net_plotter.py
NetAnalyzer/netanalyzer.py
NetAnalyzer/performancer.py
NetAnalyzer/ranker.py
NetAnalyzer/seed_parser.py
NetAnalyzer/templates/net_explorer.txt
NetAnalyzer/templates/network.txt
NetAnalyzer-1.0.0.dist-info/LICENSE.txt
NetAnalyzer-1.0.0.dist-info/METADATA
NetAnalyzer-1.0.0.dist-info/WHEEL
NetAnalyzer-1.0.0.dist-info/entry_points.txt
NetAnalyzer-1.0.0.dist-info/top_level.txt
NetAnalyzer-1.0.0.dist-info/RECORD
