Metadata-Version: 2.1
Name: NetAnalyzer
Version: 1.0.0
Summary: Python package for network analysis, operations and priorization.
Home-page: https://github.com/seoanezonjic/NetAnalyzer/
Author: seoanezonjic
Author-email: seoanezonjic@uma.es
License: MIT
Project-URL: Documentation, https://github.com/seoanezonjic/NetAnalyzer/
Platform: any
Classifier: Development Status :: 4 - Beta
Classifier: Programming Language :: Python
License-File: LICENSE.txt
Requires-Dist: NetworkX
Requires-Dist: numpy
Requires-Dist: scipy ==1.10.1
Requires-Dist: statsmodels
Requires-Dist: graphviz
Requires-Dist: mako
Requires-Dist: matplotlib
Requires-Dist: cdlib
Requires-Dist: scikit-learn
Requires-Dist: py-semtools
Requires-Dist: umap-learn
Requires-Dist: py-report-html
Requires-Dist: pecanpy
Requires-Dist: typing-extensions
Requires-Dist: py-cmdtabs
Requires-Dist: py-exp-calc
Requires-Dist: clusim
Requires-Dist: importlib-metadata ; python_version < "3.8"
Provides-Extra: testing
Requires-Dist: setuptools ; extra == 'testing'
Requires-Dist: pytest ; extra == 'testing'
Requires-Dist: pytest-cov ; extra == 'testing'
